LICENSE
MANIFEST.in
README.md
setup.py
django_uwkhtmltopdf/__init__.py
django_uwkhtmltopdf/options.py
django_uwkhtmltopdf/utils.py
django_uwkhtmltopdf.egg-info/PKG-INFO
django_uwkhtmltopdf.egg-info/SOURCES.txt
django_uwkhtmltopdf.egg-info/dependency_links.txt
django_uwkhtmltopdf.egg-info/not-zip-safe
django_uwkhtmltopdf.egg-info/requires.txt
django_uwkhtmltopdf.egg-info/top_level.txt
django_uwkhtmltopdf/tests/__init__.py
django_uwkhtmltopdf/tests/options.py