Metadata-Version: 1.1
Name: django-uwkhtmltopdf
Version: 0.5.0
Summary: A Django app to generate pdfs from templates using wkhtmltopdf
Home-page: https://github.com/xrmx/django-uwkhtmltopdf
Author: Riccardo Magliocchetti
Author-email: riccardo.magliocchetti@gmail.com
License: BSD License
Platform: OS Independent
Classifier: Environment :: Web Environment
Classifier: Framework :: Django
Classifier: Intended Audience :: Developers
Classifier: License :: OSI Approved :: BSD License
Classifier: Operating System :: OS Independent
Classifier: Programming Language :: Python
Classifier: Topic :: Software Development :: Libraries :: Application Frameworks
Classifier: Topic :: Internet :: WWW/HTTP :: Dynamic Content
